randlax/__init__.py
randlax/algorithms.py
randlax-0.3.2.dist-info/WHEEL
randlax-0.3.2.dist-info/METADATA
randlax-0.3.2.dist-info/RECORD
