Metadata-Version: 2.3
Name: randlax
Version: 0.3.2
Summary: Randomized Linear Algebra routines for JAX
Author: Joshua Chen, Michael Brennan, Thomas O'Leary-Roseberry
Author-email: Joshua Chen <joshuawchen@icloud.com>, Michael Brennan <mcbrenn@mit.edu>, Thomas O'Leary-Roseberry <tom.olearyroseberry@utexas.edu>
License: MIT License
Requires-Dist: jax
Requires-Dist: jaxlib
Requires-Dist: numpy
Requires-Dist: pytest ; extra == 'dev'
Requires-Dist: black ; extra == 'dev'
Requires-Dist: isort ; extra == 'dev'
Requires-Dist: flake8 ; extra == 'dev'
Requires-Python: >=3.9
Project-URL: Homepage, https://github.com/joshuawchen/randLAX
Project-URL: Repository, https://github.com/joshuawchen/randLAX
Provides-Extra: dev
